{"entries": [{"double": 0, "state": {"q": 1, "p": 2}, "hit": -2.0, "stand": -10.0}, {"double": 20.0, "state": {"q": 2, "p": 2}, "hit": -2.0, "stand": -10.0}, {"double": -20.0, "state": {"q": 3, "p": 2}, "hit": 5.551115123125783e-17, "stand": -10.0}, {"double": -20.0, "state": {"q": 4, "p": 2}, "hit": -5.0, "stand": -3.333333333333333}, {"double": 0, "state": {"q": 5, "p": 2}, "hit": 3.0, "stand": 0}, {"double": 20.0, "state": {"q": 6, "p": 2}, "hit": 0, "stand": 0}, {"double": -20.0, "state": {"q": 7, "p": 2}, "hit": -0.6666666666666667, "stand": -10.0}, {"double": -20.0, "state": {"q": 8, "p": 2}, "hit": 0, "stand": 0}, {"double": -20.0, "state": {"q": 9, "p": 2}, "hit": -3.5, "stand": -10.0}, {"double": -20.0, "state": {"q": 10, "p": 2}, "hit": -2.7500000000000004, "stand": -10.0}, {"double": -20.0, "state": {"q": 1, "p": 3}, "hit": -6.0, "stand": -10.0}, {"double": -20.0, "state": {"q": 2, "p": 3}, "hit": -2.25, "stand": -10.0}, {"double": 6.666666666666666, "state": {"q": 3, "p": 3}, "hit": 1.0, "stand": -10.0}, {"double": 5.000000000000002, "state": {"q": 4, "p": 3}, "hit": 0, "stand": 0}, {"double": -20.0, "state": {"q": 5, "p": 3}, "hit": -1.75, "stand": -1.1111111111111107}, {"double": -20.0, "state": {"q": 6, "p": 3}, "hit": 0.6000000000000002, "stand": -10.0}, {"double": -20.0, "state": {"q": 7, "p": 3}, "hit": -2.555555555555556, "stand": -5.0}, {"double": -20.0, "state": {"q": 8, "p": 3}, "hit": -4.000000000000001, "stand": -10.0}, {"double": -6.666666666666666, "state": {"q": 9, "p": 3}, "hit": -3.5, "stand": -10.0}, {"double": -20.0, "state": {"q": 10, "p": 3}, "hit": -3.2962962962962967, "stand": -10.0}, {"double": -20.0, "state": {"q": 1, "p": 4}, "hit": -4.571428571428572, "stand": -10.0}, {"double": -20.0, "state": {"q": 2, "p": 4}, "hit": -2.916666666666666, "stand": -10.0}, {"double": -20.0, "state": {"q": 3, "p": 4}, "hit": 0.0555555555555558, "stand": 0.0}, {"double": -6.666666666666666, "state": {"q": 4, "p": 4}, "hit": -1.1, "stand": -3.333333333333333}, {"double": -3.9999999999999987, "state": {"q": 5, "p": 4}, "hit": -2.444444444444444, "stand": -10.0}, {"double": 1.6666666666666679, "state": {"q": 6, "p": 4}, "hit": -5.0, "stand": -10.0}, {"double": -6.666666666666666, "state": {"q": 7, "p": 4}, "hit": -1.7272727272727273, "stand": -10.0}, {"double": -20.0, "state": {"q": 8, "p": 4}, "hit": -3.2222222222222223, "stand": -10.0}, {"double": -20.0, "state": {"q": 9, "p": 4}, "hit": -3.4000000000000004, "stand": -10.0}, {"double": -20.0, "state": {"q": 10, "p": 4}, "hit": -3.9375000000000013, "stand": -10.0}, {"double": -20.0, "state": {"q": 1, "p": 5}, "hit": -3.833333333333334, "stand": -10.0}, {"double": -20.0, "state": {"q": 2, "p": 5}, "hit": -2.642857142857143, "stand": -10.0}, {"double": -20.0, "state": {"q": 3, "p": 5}, "hit": -0.9230769230769231, "stand": -10.0}, {"double": -3.9999999999999987, "state": {"q": 4, "p": 5}, "hit": -2.0000000000000004, "stand": -10.0}, {"double": -20.0, "state": {"q": 5, "p": 5}, "hit": -1.1904761904761905, "stand": -10.0}, {"double": -20.0, "state": {"q": 6, "p": 5}, "hit": 0.32000000000000023, "stand": -10.0}, {"double": -20.0, "state": {"q": 7, "p": 5}, "hit": -1.9444444444444442, "stand": -10.0}, {"double": -20.0, "state": {"q": 8, "p": 5}, "hit": -3.7777777777777803, "stand": -10.0}, {"double": -20.0, "state": {"q": 9, "p": 5}, "hit": -3.083333333333333, "stand": -10.0}, {"double": -8.333333333333332, "state": {"q": 10, "p": 5}, "hit": -4.258064516129035, "stand": -7.037037037037038}, {"double": -20.0, "state": {"q": 1, "p": 6}, "hit": -5.714285714285715, "stand": -10.0}, {"double": -20.0, "state": {"q": 2, "p": 6}, "hit": -3.8823529411764706, "stand": -10.0}, {"double": -20.0, "state": {"q": 3, "p": 6}, "hit": -0.5, "stand": -10.0}, {"double": -20.0, "state": {"q": 4, "p": 6}, "hit": -1.8181818181818177, "stand": -10.0}, {"double": 2.8571428571428594, "state": {"q": 5, "p": 6}, "hit": -1.0000000000000002, "stand": -10.0}, {"double": -20.0, "state": {"q": 6, "p": 6}, "hit": -0.793103448275862, "stand": -10.0}, {"double": -20.0, "state": {"q": 7, "p": 6}, "hit": -1.2222222222222219, "stand": -10.0}, {"double": -6.666666666666666, "state": {"q": 8, "p": 6}, "hit": -3.25, "stand": -10.0}, {"double": -10.0, "state": {"q": 9, "p": 6}, "hit": -5.230769230769234, "stand": -10.0}, {"double": -7.0588235294117645, "state": {"q": 10, "p": 6}, "hit": -4.615384615384613, "stand": -10.0}, {"double": -20.0, "state": {"q": 1, "p": 7}, "hit": -5.250000000000002, "stand": -10.0}, {"double": -20.0, "state": {"q": 2, "p": 7}, "hit": -3.2857142857142856, "stand": -10.0}, {"double": -10.0, "state": {"q": 3, "p": 7}, "hit": -0.4799999999999999, "stand": -10.0}, {"double": -3.9999999999999987, "state": {"q": 4, "p": 7}, "hit": -2.0588235294117654, "stand": -4.285714285714286}, {"double": -20.0, "state": {"q": 5, "p": 7}, "hit": -2.6666666666666674, "stand": -10.0}, {"double": -20.0, "state": {"q": 6, "p": 7}, "hit": -0.5882352941176469, "stand": -10.0}, {"double": -20.0, "state": {"q": 7, "p": 7}, "hit": -1.7931034482758628, "stand": -3.333333333333334}, {"double": -2.857142857142856, "state": {"q": 8, "p": 7}, "hit": -2.4444444444444446, "stand": -10.0}, {"double": -20.0, "state": {"q": 9, "p": 7}, "hit": -4.724137931034484, "stand": -10.0}, {"double": -14.285714285714285, "state": {"q": 10, "p": 7}, "hit": -4.126126126126124, "stand": -5.0}, {"double": -20.0, "state": {"q": 1, "p": 8}, "hit": -2.5500000000000003, "stand": -3.333333333333333}, {"double": -20.0, "state": {"q": 2, "p": 8}, "hit": -2.058823529411765, "stand": -3.076923076923077}, {"double": -20.0, "state": {"q": 3, "p": 8}, "hit": -0.7777777777777778, "stand": -10.0}, {"double": -20.0, "state": {"q": 4, "p": 8}, "hit": -2.8717948717948736, "stand": -3.333333333333333}, {"double": -20.0, "state": {"q": 5, "p": 8}, "hit": -2.4999999999999996, "stand": -10.0}, {"double": -20.0, "state": {"q": 6, "p": 8}, "hit": -1.142857142857143, "stand": 1.842105263157896}, {"double": -10.0, "state": {"q": 7, "p": 8}, "hit": 1.1142857142857143, "stand": -10.0}, {"double": -3.076923076923077, "state": {"q": 8, "p": 8}, "hit": -2.6666666666666665, "stand": -5.0}, {"double": -20.0, "state": {"q": 9, "p": 8}, "hit": -6.666666666666666, "stand": -4.864864864864863}, {"double": -20.0, "state": {"q": 10, "p": 8}, "hit": -9.0, "stand": -3.671875000000001}, {"double": -10.0, "state": {"q": 1, "p": 9}, "hit": -3.4375, "stand": -10.0}, {"double": -8.000000000000002, "state": {"q": 2, "p": 9}, "hit": 0.2058823529411769, "stand": -2.500000000000001}, {"double": -5.0, "state": {"q": 3, "p": 9}, "hit": 1.4680851063829787, "stand": -10.0}, {"double": -20.0, "state": {"q": 4, "p": 9}, "hit": -1.5757575757575764, "stand": -10.0}, {"double": 5.365853658536585, "state": {"q": 5, "p": 9}, "hit": 1.75, "stand": -10.0}, {"double": 8.881784197001252e-16, "state": {"q": 6, "p": 9}, "hit": 1.6315789473684217, "stand": -10.0}, {"double": -20.0, "state": {"q": 7, "p": 9}, "hit": 2.8095238095238098, "stand": -10.0}, {"double": -20.0, "state": {"q": 8, "p": 9}, "hit": 0.21212121212121185, "stand": -10.0}, {"double": -20.0, "state": {"q": 9, "p": 9}, "hit": -5.230769230769232, "stand": -10.0}, {"double": -5.6000000000000005, "state": {"q": 10, "p": 9}, "hit": -2.94512195121951, "stand": -10.0}, {"double": -20.0, "state": {"q": 1, "p": 10}, "hit": -5.0, "stand": -2.592592592592593}, {"double": -20.0, "state": {"q": 2, "p": 10}, "hit": -0.1372549019607845, "stand": -10.0}, {"double": -6.666666666666666, "state": {"q": 3, "p": 10}, "hit": -4.0, "stand": -0.2777777777777771}, {"double": -20.0, "state": {"q": 4, "p": 10}, "hit": 0.2608695652173913, "stand": -10.0}, {"double": 10.370370370370365, "state": {"q": 5, "p": 10}, "hit": -1.5, "stand": 2.2222222222222228}, {"double": -4.999999999999998, "state": {"q": 6, "p": 10}, "hit": -1.5, "stand": 0.8333333333333336}, {"double": -20.0, "state": {"q": 7, "p": 10}, "hit": 3.10204081632653, "stand": -10.0}, {"double": -20.0, "state": {"q": 8, "p": 10}, "hit": 1.3636363636363638, "stand": -3.333333333333333}, {"double": -20.0, "state": {"q": 9, "p": 10}, "hit": -1.6304347826086962, "stand": -10.0}, {"double": -20.0, "state": {"q": 10, "p": 10}, "hit": -9.0, "stand": -1.5714285714285725}, {"double": -20.0, "state": {"q": 1, "p": 11}, "hit": 0.9999999999999999, "stand": -2.0}, {"double": -20.0, "state": {"q": 2, "p": 11}, "hit": 1.1224489795918366, "stand": -10.0}, {"double": 0.0, "state": {"q": 3, "p": 11}, "hit": 1.7142857142857153, "stand": -2.0}, {"double": -1.6666666666666659, "state": {"q": 4, "p": 11}, "hit": 0.5833333333333339, "stand": -10.0}, {"double": -1.4285714285714277, "state": {"q": 5, "p": 11}, "hit": -3.666666666666667, "stand": 2.187500000000001}, {"double": 6.249999999999999, "state": {"q": 6, "p": 11}, "hit": 0.5999999999999999, "stand": 6.0}, {"double": 9.230769230769228, "state": {"q": 7, "p": 11}, "hit": 6.666666666666668, "stand": -10.0}, {"double": -20.0, "state": {"q": 8, "p": 11}, "hit": 4.352941176470589, "stand": -10.0}, {"double": -20.0, "state": {"q": 9, "p": 11}, "hit": -0.11627906976744154, "stand": -3.333333333333334}, {"double": -20.0, "state": {"q": 10, "p": 11}, "hit": 0.7218045112781954, "stand": -6.363636363636363}, {"double": -20.0, "state": {"q": 1, "p": 12}, "hit": -5.4883720930232585, "stand": -6.666666666666666}, {"double": -9.09090909090909, "state": {"q": 2, "p": 12}, "hit": -4.2542372881355925, "stand": -6.249999999999999}, {"double": 10.0, "state": {"q": 3, "p": 12}, "hit": -4.017857142857142, "stand": -10.0}, {"double": -4.571428571428571, "state": {"q": 4, "p": 12}, "hit": -4.882352941176468, "stand": -6.0}, {"double": -12.0, "state": {"q": 5, "p": 12}, "hit": -3.7031249999999982, "stand": -10.0}, {"double": -20.0, "state": {"q": 6, "p": 12}, "hit": -2.5866666666666656, "stand": -10.0}, {"double": -5.714285714285715, "state": {"q": 7, "p": 12}, "hit": -1.0114942528735629, "stand": -8.18181818181818}, {"double": -20.0, "state": {"q": 8, "p": 12}, "hit": -4.652173913043478, "stand": -10.0}, {"double": -20.0, "state": {"q": 9, "p": 12}, "hit": -5.770491803278686, "stand": -10.0}, {"double": -20.0, "state": {"q": 10, "p": 12}, "hit": -3.538152610441766, "stand": -6.41025641025641}, {"double": -20.0, "state": {"q": 1, "p": 13}, "hit": -6.433333333333333, "stand": -10.0}, {"double": -20.0, "state": {"q": 2, "p": 13}, "hit": -10.0, "stand": -2.499999999999999}, {"double": -13.333333333333334, "state": {"q": 3, "p": 13}, "hit": -3.599999999999999, "stand": -1.549295774647887}, {"double": -20.0, "state": {"q": 4, "p": 13}, "hit": -3.1645569620253164, "stand": -6.666666666666667}, {"double": -4.999999999999998, "state": {"q": 5, "p": 13}, "hit": -3.6301369863013697, "stand": -10.0}, {"double": -8.0, "state": {"q": 6, "p": 13}, "hit": -7.333333333333335, "stand": -1.8421052631578945}, {"double": -20.0, "state": {"q": 7, "p": 13}, "hit": -2.6923076923076907, "stand": -10.0}, {"double": -20.0, "state": {"q": 8, "p": 13}, "hit": -3.98780487804878, "stand": -10.0}, {"double": -20.0, "state": {"q": 9, "p": 13}, "hit": -4.948717948717949, "stand": -10.0}, {"double": -10.588235294117647, "state": {"q": 10, "p": 13}, "hit": -10.0, "stand": -4.336917562724011}, {"double": -20.0, "state": {"q": 1, "p": 14}, "hit": -5.326530612244895, "stand": -10.0}, {"double": -6.666666666666666, "state": {"q": 2, "p": 14}, "hit": -5.137931034482756, "stand": -10.0}, {"double": -20.0, "state": {"q": 3, "p": 14}, "hit": -4.22857142857143, "stand": -10.0}, {"double": -20.0, "state": {"q": 4, "p": 14}, "hit": -5.333333333333334, "stand": -0.30303030303030287}, {"double": -10.769230769230768, "state": {"q": 5, "p": 14}, "hit": -5.818181818181819, "stand": -1.8181818181818181}, {"double": -20.0, "state": {"q": 6, "p": 14}, "hit": -3.278688524590161, "stand": -10.0}, {"double": -20.0, "state": {"q": 7, "p": 14}, "hit": -2.794520547945205, "stand": -10.0}, {"double": -20.0, "state": {"q": 8, "p": 14}, "hit": -5.986842105263158, "stand": -10.0}, {"double": -20.0, "state": {"q": 9, "p": 14}, "hit": -5.8314606741573005, "stand": -7.999999999999999}, {"double": -11.428571428571427, "state": {"q": 10, "p": 14}, "hit": -4.963114754098361, "stand": -10.0}, {"double": -20.0, "state": {"q": 1, "p": 15}, "hit": -6.280000000000001, "stand": -10.0}, {"double": -20.0, "state": {"q": 2, "p": 15}, "hit": -6.166666666666665, "stand": -2.873563218390804}, {"double": -20.0, "state": {"q": 3, "p": 15}, "hit": -4.671874999999998, "stand": -10.0}, {"double": -20.0, "state": {"q": 4, "p": 15}, "hit": -10.0, "stand": -2.987012987012988}, {"double": -20.0, "state": {"q": 5, "p": 15}, "hit": -6.0, "stand": -0.1408450704225351}, {"double": -6.666666666666666, "state": {"q": 6, "p": 15}, "hit": -3.4098360655737703, "stand": -10.0}, {"double": -5.555555555555555, "state": {"q": 7, "p": 15}, "hit": -3.584415584415584, "stand": -10.0}, {"double": -6.086956521739131, "state": {"q": 8, "p": 15}, "hit": -3.970149253731343, "stand": -10.0}, {"double": -10.0, "state": {"q": 9, "p": 15}, "hit": -6.320512820512823, "stand": -10.0}, {"double": -20.0, "state": {"q": 10, "p": 15}, "hit": -5.1406844106463865, "stand": -10.0}, {"double": -20.0, "state": {"q": 1, "p": 16}, "hit": -7.584905660377357, "stand": -10.0}, {"double": -20.0, "state": {"q": 2, "p": 16}, "hit": -5.961038961038961, "stand": -10.0}, {"double": -20.0, "state": {"q": 3, "p": 16}, "hit": -7.692307692307694, "stand": -1.3043478260869568}, {"double": -10.000000000000002, "state": {"q": 4, "p": 16}, "hit": -6.750000000000001, "stand": -2.82051282051282}, {"double": -20.0, "state": {"q": 5, "p": 16}, "hit": -4.636363636363633, "stand": -10.0}, {"double": -20.0, "state": {"q": 6, "p": 16}, "hit": -5.603448275862065, "stand": -10.0}, {"double": -20.0, "state": {"q": 7, "p": 16}, "hit": -4.843373493975904, "stand": -10.0}, {"double": -20.0, "state": {"q": 8, "p": 16}, "hit": -7.5, "stand": -4.814814814814815}, {"double": -20.0, "state": {"q": 9, "p": 16}, "hit": -6.5402298850574745, "stand": -10.0}, {"double": -20.0, "state": {"q": 10, "p": 16}, "hit": -6.3852140077821025, "stand": -10.0}, {"double": -10.0, "state": {"q": 1, "p": 17}, "hit": -7.5957446808510625, "stand": -10.0}, {"double": -20.0, "state": {"q": 2, "p": 17}, "hit": -6.164383561643836, "stand": -10.0}, {"double": -20.0, "state": {"q": 3, "p": 17}, "hit": -5.281690140845073, "stand": -10.0}, {"double": -20.0, "state": {"q": 4, "p": 17}, "hit": -10.000000000000002, "stand": -1.2698412698412695}, {"double": -20.0, "state": {"q": 5, "p": 17}, "hit": -10.0, "stand": -0.16666666666666674}, {"double": -20.0, "state": {"q": 6, "p": 17}, "hit": -8.750000000000002, "stand": -1.1267605633802817}, {"double": -20.0, "state": {"q": 7, "p": 17}, "hit": -5.333333333333334, "stand": -2.075471698113209}, {"double": -20.0, "state": {"q": 8, "p": 17}, "hit": -7.333333333333334, "stand": -4.6987951807228905}, {"double": -20.0, "state": {"q": 9, "p": 17}, "hit": -7.027027027027028, "stand": -10.0}, {"double": -20.0, "state": {"q": 10, "p": 17}, "hit": -6.421875000000002, "stand": -4.507042253521126}, {"double": -7.999999999999999, "state": {"q": 1, "p": 18}, "hit": -10.0, "stand": 0.5263157894736843}, {"double": -20.0, "state": {"q": 2, "p": 18}, "hit": -10.0, "stand": 1.06060606060606}, {"double": -20.0, "state": {"q": 3, "p": 18}, "hit": -10.0, "stand": 0.8955223880597012}, {"double": -20.0, "state": {"q": 4, "p": 18}, "hit": -5.104477611940299, "stand": -10.0}, {"double": -11.11111111111111, "state": {"q": 5, "p": 18}, "hit": -7.770491803278685, "stand": -10.0}, {"double": -20.0, "state": {"q": 6, "p": 18}, "hit": -7.500000000000002, "stand": 2.8571428571428554}, {"double": -20.0, "state": {"q": 7, "p": 18}, "hit": -6.142857142857144, "stand": 5.412844036697251}, {"double": -20.0, "state": {"q": 8, "p": 18}, "hit": -10.0, "stand": 1.4925373134328357}, {"double": -20.0, "state": {"q": 9, "p": 18}, "hit": -7.531914893617023, "stand": -10.0}, {"double": -20.0, "state": {"q": 10, "p": 18}, "hit": -10.000000000000002, "stand": -2.39819004524887}, {"double": -20.0, "state": {"q": 1, "p": 19}, "hit": -10.0, "stand": 1.7241379310344818}, {"double": -20.0, "state": {"q": 2, "p": 19}, "hit": -10.0, "stand": 4.788732394366198}, {"double": -20.0, "state": {"q": 3, "p": 19}, "hit": -6.1111111111111125, "stand": 4.09090909090909}, {"double": -20.0, "state": {"q": 4, "p": 19}, "hit": -10.0, "stand": 5.454545454545457}, {"double": -20.0, "state": {"q": 5, "p": 19}, "hit": -10.000000000000002, "stand": 5.531914893617022}, {"double": -6.666666666666666, "state": {"q": 6, "p": 19}, "hit": -10.0, "stand": 5.714285714285715}, {"double": -20.0, "state": {"q": 7, "p": 19}, "hit": -10.0, "stand": 7.171717171717173}, {"double": -20.0, "state": {"q": 8, "p": 19}, "hit": -6.833333333333334, "stand": 6.428571428571427}, {"double": -20.0, "state": {"q": 9, "p": 19}, "hit": -7.7446808510638325, "stand": -10.0}, {"double": -20.0, "state": {"q": 10, "p": 19}, "hit": -10.000000000000002, "stand": 0.6521739130434783}, {"double": -20.0, "state": {"q": 1, "p": 20}, "hit": -8.543859649122803, "stand": -10.0}, {"double": -6.666666666666665, "state": {"q": 2, "p": 20}, "hit": -10.0, "stand": 5.777777777777775}, {"double": -20.0, "state": {"q": 3, "p": 20}, "hit": -10.0, "stand": 5.757575757575759}, {"double": -20.0, "state": {"q": 4, "p": 20}, "hit": -10.0, "stand": 5.777777777777774}, {"double": -20.0, "state": {"q": 5, "p": 20}, "hit": -10.0, "stand": 7.499999999999999}, {"double": -20.0, "state": {"q": 6, "p": 20}, "hit": -6.666666666666667, "stand": 6.129032258064517}, {"double": -20.0, "state": {"q": 7, "p": 20}, "hit": -10.0, "stand": 8.235294117647058}, {"double": -10.0, "state": {"q": 8, "p": 20}, "hit": -10.0, "stand": 7.976190476190478}, {"double": -20.0, "state": {"q": 9, "p": 20}, "hit": -6.2857142857142865, "stand": 8.211382113821147}, {"double": -20.0, "state": {"q": 10, "p": 20}, "hit": -10.000000000000002, "stand": 5.7366771159874625}, {"double": 0, "state": {"q": 1, "p": 21}, "hit": -10.0, "stand": 8.709677419354842}, {"double": 0, "state": {"q": 2, "p": 21}, "hit": 0, "stand": 8.787878787878789}, {"double": 0, "state": {"q": 3, "p": 21}, "hit": 0, "stand": 8.947368421052634}, {"double": 0, "state": {"q": 4, "p": 21}, "hit": -10.0, "stand": 8.387096774193548}, {"double": 0, "state": {"q": 5, "p": 21}, "hit": -10.0, "stand": 8.461538461538463}, {"double": 0, "state": {"q": 6, "p": 21}, "hit": 0, "stand": 8.947368421052632}, {"double": 0, "state": {"q": 7, "p": 21}, "hit": -10.0, "stand": 9.375000000000005}, {"double": 0, "state": {"q": 8, "p": 21}, "hit": 0, "stand": 10.000000000000004}, {"double": 0, "state": {"q": 9, "p": 21}, "hit": -10.0, "stand": 9.508196721311473}, {"double": 0, "state": {"q": 10, "p": 21}, "hit": -10.0, "stand": 9.59677419354839}]}